setup.py
collections/deque.py
micropython_collections.deque.egg-info/PKG-INFO
micropython_collections.deque.egg-info/SOURCES.txt
micropython_collections.deque.egg-info/dependency_links.txt
micropython_collections.deque.egg-info/top_level.txt