Metadata-Version: 1.0
Name: micropython-collections.deque
Version: 0.1.1
Summary: collections.deque module for MicroPython
Home-page: https://github.com/micropython/micropython/issues/405
Author: MicroPython Developers
Author-email: micro-python@googlegroups.com
License: MIT
Platform: UNKNOWN
